tinker/__init__.py
tinker/algorithm.py
tinker/configuration.py
tinker/main.py
tinker/protocol.py
tinker/py.typed
tinker_engine-0.10.1.dist-info/LICENSE
tinker_engine-0.10.1.dist-info/WHEEL
tinker_engine-0.10.1.dist-info/METADATA
tinker_engine-0.10.1.dist-info/RECORD
