Metadata-Version: 2.1
Name: tinker-engine
Version: 0.10.1
Summary: Framework for configuring and running machine learning algorithms
License: Apache-2.0
Author: Roni Choudhury
Author-email: roni.choudhury@kitware.com
Requires-Python: >=3.7,<4.0
Classifier: License :: OSI Approved :: Apache Software License
Classifier: Programming Language :: Python :: 3
Classifier: Programming Language :: Python :: 3.10
Classifier: Programming Language :: Python :: 3.7
Classifier: Programming Language :: Python :: 3.8
Classifier: Programming Language :: Python :: 3.9
Requires-Dist: click (>=8.1.2,<9.0.0)
Requires-Dist: pyyaml (>=5.4.1,<6.0.0)
Requires-Dist: smqtk-core (==0.18.1)
Requires-Dist: types-PyYAML (>=6.0.5,<7.0.0)
